{
	"data": {
		"product": {
			"id": "gid://shopify/Product/8688221520220",
			"handle": "pla-silk-dual-color",
			"title": "PLA Silk Dual Color",
			"vendor": "Bambu Lab EU",
			"availableForSale": true,
			"onlineStoreUrl": "https://eu.store.bambulab.com/en-pt/products/pla-silk-dual-color",
			"tags": [
				"Compatible with AMS",
				"Cosmetic",
				"filaments",
				"For P1 Series",
				"For X1 Series",
				"Multi",
				"On Sale"
			],
			"publishedAt": "2024-01-04T09:15:59Z",
			"priceRange": {
				"maxVariantPrice": {
					"amount": "28.93"
				},
				"minVariantPrice": {
					"amount": "28.93"
				}
			},
			"featuredImage": {
				"id": "gid://shopify/ProductImage/72130250834268",
				"url": "https://cdn.shopify.com/s/files/1/0645/5876/0155/files/PLA_Silk_dual_color-new_244c14cb-fcf3-46ba-ad82-e93ebbdbb24b.png?v=1732529073"
			},
			"options": [
				{
					"id": "gid://shopify/ProductOption/11292067889500",
					"name": "Type",
					"values": [
						"Filament with spool"
					],
					"optionValues": [
						{
							"id": "gid://shopify/ProductOptionValue/1146711933276",
							"name": "Filament with spool"
						}
					]
				},
				{
					"id": "gid://shopify/ProductOption/11292067922268",
					"name": "Size",
					"values": [
						"1 kg"
					],
					"optionValues": [
						{
							"id": "gid://shopify/ProductOptionValue/1146711966044",
							"name": "1 kg"
						}
					]
				},
				{
					"id": "gid://shopify/ProductOption/11292067955036",
					"name": "Color",
					"values": [
						"Velvet Eclipse (13905)",
						"Neon City (13903)",
						"Midnight Blaze (13902)",
						"Gilded Rose (13901)",
						"Blue Hawaii (13904)"
					],
					"optionValues": [
						{
							"id": "gid://shopify/ProductOptionValue/8750118732124",
							"name": "Velvet Eclipse (13905)"
						},
						{
							"id": "gid://shopify/ProductOptionValue/1146712064348",
							"name": "Neon City (13903)"
						},
						{
							"id": "gid://shopify/ProductOptionValue/1146712031580",
							"name": "Midnight Blaze (13902)"
						},
						{
							"id": "gid://shopify/ProductOptionValue/1146711998812",
							"name": "Gilded Rose (13901)"
						},
						{
							"id": "gid://shopify/ProductOptionValue/1146712097116",
							"name": "Blue Hawaii (13904)"
						}
					]
				}
			],
			"images": {
				"nodes": [
					{
						"id": "gid://shopify/ProductImage/72130250834268",
						"url": "https://cdn.shopify.com/s/files/1/0645/5876/0155/files/PLA_Silk_dual_color-new_244c14cb-fcf3-46ba-ad82-e93ebbdbb24b.png?v=1732529073",
						"altText": null
					},
					{
						"id": "gid://shopify/ProductImage/52150260105564",
						"url": "https://cdn.shopify.com/s/files/1/0645/5876/0155/files/neoncity.png?v=1704278415",
						"altText": null
					},
					{
						"id": "gid://shopify/ProductImage/52149653799260",
						"url": "https://cdn.shopify.com/s/files/1/0645/5876/0155/files/silkmodel3.png?v=1704278415",
						"altText": null
					},
					{
						"id": "gid://shopify/ProductImage/52152163795292",
						"url": "https://cdn.shopify.com/s/files/1/0645/5876/0155/files/midnightblaze2.png?v=1704359777",
						"altText": null
					},
					{
						"id": "gid://shopify/ProductImage/52163631710556",
						"url": "https://cdn.shopify.com/s/files/1/0645/5876/0155/files/cutedragonmodel2.png?v=1704359777",
						"altText": null
					},
					{
						"id": "gid://shopify/ProductImage/52150260007260",
						"url": "https://cdn.shopify.com/s/files/1/0645/5876/0155/files/glidedrose.png?v=1704359777",
						"altText": null
					},
					{
						"id": "gid://shopify/ProductImage/52150260040028",
						"url": "https://cdn.shopify.com/s/files/1/0645/5876/0155/files/blueHawaii.png?v=1704359777",
						"altText": null
					}
				]
			},
			"variants": {
				"nodes": [
					{
						"id": "gid://shopify/ProductVariant/53515458085212",
						"availableForSale": true,
						"quantityAvailable": 2382,
						"compareAtPrice": null,
						"selectedOptions": [
							{
								"name": "Type",
								"value": "Filament with spool"
							},
							{
								"name": "Size",
								"value": "1 kg"
							},
							{
								"name": "Color",
								"value": "Velvet Eclipse (13905)"
							}
						],
						"currentlyNotInStock": false,
						"featured_image": {
							"id": "gid://shopify/ProductImage/72130250834268",
							"src": "https://cdn.shopify.com/s/files/1/0645/5876/0155/files/PLA_Silk_dual_color-new_244c14cb-fcf3-46ba-ad82-e93ebbdbb24b.png?v=1732529073",
							"altText": null
						},
						"price": {
							"currencyCode": "EUR",
							"amount": "28.93"
						},
						"title": "Filament with spool / 1 kg / Velvet Eclipse (13905)",
						"sku": "A05-T5-1.75-1000-SPL"
					},
					{
						"id": "gid://shopify/ProductVariant/47489270841692",
						"availableForSale": true,
						"quantityAvailable": 2294,
						"compareAtPrice": null,
						"selectedOptions": [
							{
								"name": "Type",
								"value": "Filament with spool"
							},
							{
								"name": "Size",
								"value": "1 kg"
							},
							{
								"name": "Color",
								"value": "Neon City (13903)"
							}
						],
						"currentlyNotInStock": false,
						"featured_image": {
							"id": "gid://shopify/ProductImage/52150260105564",
							"src": "https://cdn.shopify.com/s/files/1/0645/5876/0155/files/neoncity.png?v=1704278415",
							"altText": null
						},
						"price": {
							"currencyCode": "EUR",
							"amount": "28.93"
						},
						"title": "Filament with spool / 1 kg / Neon City (13903)",
						"sku": "A05-T3-1.75-1000-SPL"
					},
					{
						"id": "gid://shopify/ProductVariant/47489270808924",
						"availableForSale": true,
						"quantityAvailable": 3099,
						"compareAtPrice": null,
						"selectedOptions": [
							{
								"name": "Type",
								"value": "Filament with spool"
							},
							{
								"name": "Size",
								"value": "1 kg"
							},
							{
								"name": "Color",
								"value": "Midnight Blaze (13902)"
							}
						],
						"currentlyNotInStock": false,
						"featured_image": {
							"id": "gid://shopify/ProductImage/52152163795292",
							"src": "https://cdn.shopify.com/s/files/1/0645/5876/0155/files/midnightblaze2.png?v=1704359777",
							"altText": null
						},
						"price": {
							"currencyCode": "EUR",
							"amount": "28.93"
						},
						"title": "Filament with spool / 1 kg / Midnight Blaze (13902)",
						"sku": "A05-T2-1.75-1000-SPL"
					},
					{
						"id": "gid://shopify/ProductVariant/47489270776156",
						"availableForSale": true,
						"quantityAvailable": 3251,
						"compareAtPrice": null,
						"selectedOptions": [
							{
								"name": "Type",
								"value": "Filament with spool"
							},
							{
								"name": "Size",
								"value": "1 kg"
							},
							{
								"name": "Color",
								"value": "Gilded Rose (13901)"
							}
						],
						"currentlyNotInStock": false,
						"featured_image": {
							"id": "gid://shopify/ProductImage/52150260007260",
							"src": "https://cdn.shopify.com/s/files/1/0645/5876/0155/files/glidedrose.png?v=1704359777",
							"altText": null
						},
						"price": {
							"currencyCode": "EUR",
							"amount": "28.93"
						},
						"title": "Filament with spool / 1 kg / Gilded Rose (13901)",
						"sku": "A05-T1-1.75-1000-SPL"
					},
					{
						"id": "gid://shopify/ProductVariant/47489270874460",
						"availableForSale": true,
						"quantityAvailable": 6306,
						"compareAtPrice": null,
						"selectedOptions": [
							{
								"name": "Type",
								"value": "Filament with spool"
							},
							{
								"name": "Size",
								"value": "1 kg"
							},
							{
								"name": "Color",
								"value": "Blue Hawaii (13904)"
							}
						],
						"currentlyNotInStock": false,
						"featured_image": {
							"id": "gid://shopify/ProductImage/52150260040028",
							"src": "https://cdn.shopify.com/s/files/1/0645/5876/0155/files/blueHawaii.png?v=1704359777",
							"altText": null
						},
						"price": {
							"currencyCode": "EUR",
							"amount": "28.93"
						},
						"title": "Filament with spool / 1 kg / Blue Hawaii (13904)",
						"sku": "A05-T4-1.75-1000-SPL"
					}
				]
			},
			"compareAtPriceRange": {
				"maxVariantPrice": {
					"amount": "0.0"
				},
				"minVariantPrice": {
					"amount": "0.0"
				}
			}
		}
	},
	"extensions": {
		"context": {
			"country": "PT",
			"language": "EN"
		}
	}
}
